{
  "openapi": "3.0.4",
  "info": {
    "title": "My API",
    "version": "v1"
  },
  "paths": {
    "/api/Users/register": {
      "post": {
        "tags": [
          "Users"
        ],
        "requestBody": {
          "content": {
            "application/json": {
              "schema": {
                "$ref": "#/components/schemas/RegisterRequest"
              }
            },
            "text/json": {
              "schema": {
                "$ref": "#/components/schemas/RegisterRequest"
              }
            },
            "application/*+json": {
              "schema": {
                "$ref": "#/components/schemas/RegisterRequest"
              }
            }
          }
        },
        "responses": {
          "200": {
            "description": "OK"
          }
        }
      }
    },
    "/api/Users/login": {
      "post": {
        "tags": [
          "Users"
        ],
        "requestBody": {
          "content": {
            "application/json": {
              "schema": {
                "$ref": "#/components/schemas/LoginRequest"
              }
            },
            "text/json": {
              "schema": {
                "$ref": "#/components/schemas/LoginRequest"
              }
            },
            "application/*+json": {
              "schema": {
                "$ref": "#/components/schemas/LoginRequest"
              }
            }
          }
        },
        "responses": {
          "200": {
            "description": "OK"
          }
        }
      }
    }
  },
  "components": {
    "schemas": {
      "LoginRequest": {
        "required": [
          "login",
          "password"
        ],
        "type": "object",
        "properties": {
          "login": {
            "type": "string",
            "nullable": true
          },
          "password": {
            "type": "string",
            "nullable": true
          }
        },
        "additionalProperties": false
      },
      "RegisterRequest": {
        "required": [
          "login",
          "name",
          "password"
        ],
        "type": "object",
        "properties": {
          "login": {
            "type": "string",
            "nullable": true
          },
          "password": {
            "type": "string",
            "nullable": true
          },
          "name": {
            "type": "string",
            "nullable": true
          }
        },
        "additionalProperties": false
      }
    }
  }
}